{
	"moduleDescription" :
	{
	    "name" : 		"Meta Analysis",
		"title" : 		"Meta-Analyse",
		"description" : "Meta-Analysis module.",
		"icon":			"meta-analysis.svg",
		"version":		1,
		"author":		"JASP Team",
		"maintainer":	"JASP Team <jasp-stats.org>",
		"website":		"jasp-stats.org",
		"license":		"GPL (>= 2)",
		"dynamic":		false
	},

	"requiredPackages":	[],

	"menu":  [
		{
			"title":		"Klassieke Meta-Analyse",
			"function":		"ClassicalMetaAnalysis"
		},
		{
			"title":		"-"
		},
		{
			"title": 		"Bayesiaanse Meta-Analyse",
			"function":		"BayesianMetaAnalysis"
		},
		{
			"title": 		"Robuste Bayesiaanse Meta-Analyse (beta)",
			"function":		"RobustBayesianMetaAnalysis",
			"requiresData":	false
		}
	]
}
